SQLiteAsJSON/SQLiteAsJSON.py
SQLiteAsJSON/__init__.py
SQLiteAsJSON-1.0.4.dist-info/LICENSE
SQLiteAsJSON-1.0.4.dist-info/METADATA
SQLiteAsJSON-1.0.4.dist-info/WHEEL
SQLiteAsJSON-1.0.4.dist-info/top_level.txt
SQLiteAsJSON-1.0.4.dist-info/RECORD
