Metadata-Version: 2.1
Name: SQLiteAsJSON
Version: 1.0.4
Summary: Do SQLite CRUD operation via JSON object
Home-page: https://github.com/Sajjal/SQLite_As_JSON
Author: Sajjal Neupane (https://mrsajjal.com)
License: UNKNOWN
Keywords: sqlite as json,sql json,sqlite orm,sqlite nosql,sqlite json,json sqlite
Platform: UNKNOWN
Classifier: Development Status :: 5 - Production/Stable
Classifier: Intended Audience :: Developers
Classifier: Programming Language :: Python :: 3
Classifier: Programming Language :: Python :: 3.8
Classifier: License :: OSI Approved :: MIT License
Classifier: Operating System :: Unix
Classifier: Operating System :: MacOS :: MacOS X
Classifier: Operating System :: Microsoft :: Windows
